pygtlink/ClientSocket.py
pygtlink/IgtlHeader.py
pygtlink/IgtlMessageBase.py
pygtlink/ImageMessage2.py
pygtlink/PositionMessage.py
pygtlink/SensorMessage.py
pygtlink/ServerSocket.py
pygtlink/StatusMessage.py
pygtlink/__init__.py
pygtlink/utils.py
pygtlink-1.0.0.dist-info/LICENSE
pygtlink-1.0.0.dist-info/METADATA
pygtlink-1.0.0.dist-info/WHEEL
pygtlink-1.0.0.dist-info/top_level.txt
pygtlink-1.0.0.dist-info/RECORD
