Metadata-Version: 2.1
Name: pygtlink
Version: 1.0.0
Summary: A package to handle basic openigtlink message with python
Home-page: https://github.com/mariatirindelli/PyOpenIgtlink
Author: Maria Tirindelli
Author-email: maria.tirindelli@hotmail.it
License: UNKNOWN
Platform: UNKNOWN
Classifier: Programming Language :: Python :: 3
Classifier: License :: OSI Approved :: MIT License
Classifier: Operating System :: OS Independent
Requires-Python: >=3.6
Requires-Dist: crcmod
Requires-Dist: numpy
